<?xml version="1.0" encoding="utf-8"?>
<exceptions>
    <exception package="com.google.android.gms">
        <permission name="android.permission.READ_PHONE_STATE" fixed="false"/>
        <permission name="android.permission.RECEIVE_SMS" fixed="false" whitelisted="true" />
        <permission name="android.permission.READ_CONTACTS" fixed="false"/>
        <permission name="android.permission.WRITE_CONTACTS" fixed="false"/>
        <permission name="android.permission.GET_ACCOUNTS" fixed="false"/>
        <permission name="android.permission.ACCESS_FINE_LOCATION" fixed="false"/>
        <permission name="android.permission.ACCESS_COARSE_LOCATION" fixed="false"/>
        <permission name="android.permission.READ_EXTERNAL_STORAGE" fixed="false"/>
        <permission name="android.permission.WRITE_EXTERNAL_STORAGE" fixed="false"/>
    </exception>
</exceptions>
